ThalamusEngine/Interface.py
ThalamusEngine/__init__.py
ThalamusEngine/Lib/DLLList_Readme.txt
ThalamusEngine/Lib/freeglut.dll
ThalamusEngine/Lib/opencv_world450d.dll
ThalamusEngine/Lib/thalamus.dll
ThalamusEngine/Lib/thalamus.so
ThalamusEngine-0.3.3.dist-info/METADATA
ThalamusEngine-0.3.3.dist-info/WHEEL
ThalamusEngine-0.3.3.dist-info/top_level.txt
ThalamusEngine-0.3.3.dist-info/RECORD
