Metadata-Version: 2.1
Name: ThalamusEngine
Version: 0.3.3
Summary: ThalamusEngine for Recognition of 3D
Home-page: https://github.com/Thomas-Anderson1999
Author: Thomas A. Anderson
Author-email: pjtthalamus@gmail.com
License: MIT
Keywords: OpenGL,Renderer,Thalamus
Platform: UNKNOWN
Requires-Python: >=3.6
Requires-Dist: opencv-contrib-python >=4.0
Requires-Dist: opencv-python >=4.0
